refineryframe/__init__.py
refineryframe/demo.py
refineryframe/detect_unexpected.py
refineryframe/other.py
refineryframe/refiner.py
refineryframe/replace_unexpected.py
tests/__init__.py
tests/conftest.py
tests/test_detect_unexpected.py
tests/test_refiner.py
refineryframe-0.2.2.dist-info/LICENSE
refineryframe-0.2.2.dist-info/METADATA
refineryframe-0.2.2.dist-info/WHEEL
refineryframe-0.2.2.dist-info/top_level.txt
refineryframe-0.2.2.dist-info/RECORD
