Metadata-Version: 2.1
Name: refineryframe
Version: 0.2.2
Summary: Cleans data, best to be used as a part of initial preprocessor
Author: Kyrylo Mordan
Author-email: <parachute.repo@gmail.com>
Keywords: python,data cleaning,safeguards
Classifier: Development Status :: 4 - Beta
Classifier: Intended Audience :: Developers
Classifier: Intended Audience :: Science/Research
Classifier: Programming Language :: Python :: 3
Classifier: Programming Language :: Python :: 3.8
Classifier: Programming Language :: Python :: 3.9
Classifier: Programming Language :: Python :: 3.10
Classifier: License :: OSI Approved :: MIT License
Classifier: Topic :: Scientific/Engineering
License-File: LICENSE
Requires-Dist: attrs >=22.2.0
Requires-Dist: datetime
Requires-Dist: pandas
Requires-Dist: numpy
Requires-Dist: unidecode
